confluent_kafka_config/__init__.py
confluent_kafka_config/ckc.py
confluent_kafka_config/client_pool.py
confluent_kafka_config/consumer_context.py
confluent_kafka_config/producer_context.py
confluent_kafka_config/registry_context.py
confluent_kafka_config/topic_context.py
confluent_kafka_config/utils.py
confluent_kafka_config/validation.py
confluent_kafka_config-1.1.4.dist-info/LICENCE
confluent_kafka_config-1.1.4.dist-info/METADATA
confluent_kafka_config-1.1.4.dist-info/WHEEL
confluent_kafka_config-1.1.4.dist-info/entry_points.txt
confluent_kafka_config-1.1.4.dist-info/top_level.txt
confluent_kafka_config-1.1.4.dist-info/RECORD
