Metadata-Version: 2.1
Name: confluent-kafka-config
Version: 1.1.4
Summary: Load all your confluent-kafka clients from config file.
Author-email: Lazar Jovanovic <l.jovanovic97@gmail.com>
Project-URL: Homepage, https://github.com/Aragonski97/confluent-kafka-config
Project-URL: Changelog, https://github.com/Aragonski97/confluent-kafka-config/releases
Project-URL: Issues, https://github.com/Aragonski97/confluent-kafka-config/issues
Classifier: License :: OSI Approved :: Apache Software License
Classifier: Development Status :: 4 - Beta
Classifier: Operating System :: POSIX :: Linux
Classifier: Programming Language :: Python :: 3.12
Classifier: Framework :: Pydantic :: 2
Classifier: Intended Audience :: Developers
Classifier: Topic :: Utilities
Classifier: Topic :: System :: Software Distribution
Requires-Python: >=3.12
License-File: LICENCE
Requires-Dist: annotated-types==0.7.0
Requires-Dist: anyio==4.7.0
Requires-Dist: attrs==24.3.0
Requires-Dist: avro==1.12.0
Requires-Dist: cachetools==5.5.0
Requires-Dist: casefy==1.0.0
Requires-Dist: certifi==2024.12.14
Requires-Dist: charset-normalizer==3.4.1
Requires-Dist: confluent-kafka==2.7.0
Requires-Dist: dacite==1.8.1
Requires-Dist: dataclasses-avroschema==0.65.7
Requires-Dist: dnspython==2.7.0
Requires-Dist: email_validator==2.2.0
Requires-Dist: fastavro==1.10.0
Requires-Dist: h11==0.14.0
Requires-Dist: httpcore==1.0.7
Requires-Dist: httpx==0.27.2
Requires-Dist: idna==3.10
Requires-Dist: inflection==0.5.1
Requires-Dist: pydantic==2.10.4
Requires-Dist: pydantic-settings==2.7.0
Requires-Dist: pydantic_core==2.27.2
Requires-Dist: python-dateutil==2.9.0.post0
Requires-Dist: python-dotenv==1.0.1
Requires-Dist: PyYAML==6.0.2
Requires-Dist: requests==2.32.3
Requires-Dist: setuptools==75.6.0
Requires-Dist: six==1.17.0
Requires-Dist: sniffio==1.3.1
Requires-Dist: structlog==24.4.0
Requires-Dist: typing_extensions==4.12.2
Requires-Dist: urllib3==2.3.0
Requires-Dist: wheel==0.45.1
